Metadata-Version: 2.1
Name: duote
Version: 0.1.9
Summary: 测试版本,基本功能
Author: JinxAndLux
Author-email: yby1234@hotmail.com
License: UNKNOWN
Platform: UNKNOWN
